vcolors/__init__.py
vcolors/vcolors.py
vcolors-1.3.dist-info/LICENSE
vcolors-1.3.dist-info/METADATA
vcolors-1.3.dist-info/WHEEL
vcolors-1.3.dist-info/top_level.txt
vcolors-1.3.dist-info/RECORD
