Metadata-Version: 2.1
Name: vcolors
Version: 1.3
Summary: Your terminal colored and pretty printed
Home-page: UNKNOWN
Author: Victor Valar
Author-email: <victor@valar.codes>
License: UNKNOWN
Keywords: python,colored,Color_Console,print,terminal
Platform: UNKNOWN
Classifier: Development Status :: 5 - Production/Stable
Classifier: Intended Audience :: Developers
Classifier: Programming Language :: Python :: 3
Classifier: Operating System :: Unix
Classifier: Operating System :: MacOS :: MacOS X
Classifier: Operating System :: Microsoft :: Windows
License-File: LICENSE
Requires-Dist: Color-Console (==10.0)
